motheme/__init__.py
motheme/cli.py
motheme/operations/__init__.py
motheme/operations/apply_theme.py
motheme/operations/clear_theme.py
motheme/operations/create_theme.py
motheme/operations/current_theme.py
motheme/operations/font.py
motheme/operations/list_theme.py
motheme/operations/remove_theme.py
motheme/utils/__init__.py
motheme/utils/app_parser.py
motheme/utils/file_utils.py
motheme/utils/git_utils.py
motheme/utils/io_utils.py
motheme/utils/theme_downloader.py
motheme/utils/theme_utils.py
motheme-0.2.0.dist-info/METADATA
motheme-0.2.0.dist-info/WHEEL
motheme-0.2.0.dist-info/entry_points.txt
motheme-0.2.0.dist-info/licenses/LICENSE
motheme-0.2.0.dist-info/RECORD
