Metadata-Version: 2.4
Name: motheme
Version: 0.2.0
Summary: Marimo Theming Management
Project-URL: Homepage, https://github.com/metaboulie/marimo-themes
Project-URL: Repository, https://github.com/metaboulie/marimo-themes
Author-email: métaboulie <metaboulie@pm.me>
License: 
License-File: LICENSE
Classifier: Environment :: Console
Classifier: Environment :: Web Environment
Classifier: Intended Audience :: Developers
Classifier: Intended Audience :: Education
Classifier: Intended Audience :: Science/Research
Classifier: License :: OSI Approved :: Apache Software License
Classifier: Operating System :: OS Independent
Classifier: Programming Language :: Python
Classifier: Programming Language :: Python :: 3
Classifier: Programming Language :: Python :: 3.9
Classifier: Programming Language :: Python :: 3.10
Classifier: Programming Language :: Python :: 3.11
Classifier: Programming Language :: Python :: 3.12
Classifier: Programming Language :: Python :: 3.13
Requires-Python: >=3.9
Requires-Dist: appdirs>=1.4.4
Requires-Dist: arguably>=1.3.0
Requires-Dist: requests>=2.32.3
Provides-Extra: dev
Requires-Dist: hatch>=1.13.0; extra == 'dev'
Requires-Dist: marimo>=0.9.14; extra == 'dev'
Requires-Dist: ruff>=0.7.1; extra == 'dev'
Provides-Extra: test
Requires-Dist: pytest>=8.3.4; extra == 'test'
